imp/__init__.py
imp/main.py
imp_toolkit_logs-0.1.4.dist-info/METADATA
imp_toolkit_logs-0.1.4.dist-info/WHEEL
imp_toolkit_logs-0.1.4.dist-info/entry_points.txt
imp_toolkit_logs-0.1.4.dist-info/RECORD
