Metadata-Version: 2.1
Name: imp-toolkit-logs
Version: 0.1.4
Summary: toolkit imp
Author: Johan Bustos
Author-email: johan.bustosm@gmail.com
Requires-Python: >=3.9,<4.0
Classifier: Programming Language :: Python :: 3
Classifier: Programming Language :: Python :: 3.9
Classifier: Programming Language :: Python :: 3.10
Classifier: Programming Language :: Python :: 3.11
Requires-Dist: click (>=8.1.6,<9.0.0)
Requires-Dist: gitpython (>=3.1.32,<4.0.0)
